final_project/hdl/bin2bcd.sv
`timescale 1ns / 1ps
`default_nettype none

module bin2bcd (
    input wire clk_in,
    input wire rst_in,
    input wire [11:0] bin,
    input wire data_valid_in,
    output logic [15:0] bcd_out
    );

    logic [4:0] i; // run for 12 iterations

    typedef enum {IDLE = 0 ,INITIALIZE=1, BCD = 2, BCD_CHECK = 3, OUTPUT = 4} current_state;
    current_state state;
    logic [15:0] bcd_temp;

    always_ff @(posedge clk_in) begin
        if (rst_in) begin
            bcd_temp <= 16'b0;
            bcd_out <= 16'b0;
            i <= 5'b0;
            state <= INITIALIZE;
        end else begin
            case (state)
            IDLE: begin
                if (data_valid_in) begin
                state <= INITIALIZE;
                end else begin
                    state <= IDLE;
                end
            end
            INITIALIZE: begin
                bcd_temp <= 0;
                i <= 0;
                state <= BCD;
            end
            BCD: begin
                if (i < 12) begin
                    //bcd_temp <= {bcd_temp[15:1],bin[11-i]};
                    bcd_temp[15] <= bcd_temp[14];
                    bcd_temp[14] <= bcd_temp[13];
                    bcd_temp[13] <= bcd_temp[12];
                    bcd_temp[12] <= bcd_temp[11];
                    bcd_temp[11] <= bcd_temp[10];
                    bcd_temp[10] <= bcd_temp[9];
                    bcd_temp[9] <= bcd_temp[8];
                    bcd_temp[8] <= bcd_temp[7];
                    bcd_temp[7] <= bcd_temp[6];
                    bcd_temp[6] <= bcd_temp[5];
                    bcd_temp[5] <= bcd_temp[4];
                    bcd_temp[4] <= bcd_temp[3];
                    bcd_temp[3] <= bcd_temp[2];
                    bcd_temp[2] <= bcd_temp[1];
                    bcd_temp[1] <= bcd_temp[0];
                    bcd_temp[0] <= bin[11-i];

                    state <= BCD_CHECK;
                end else begin
                    bcd_out <= bcd_temp;
                    i <= 0;
                    state <= OUTPUT;
                end
            end
            BCD_CHECK: begin
                if (i < 11 && bcd_temp[3:0] > 4) begin
                    bcd_temp[3:0] <= bcd_temp[3:0] + 3;
                end else begin
                end
                if (i < 11 && bcd_temp[7:4] > 4) begin
                    bcd_temp[7:4] <= bcd_temp[7:4] + 3;
                end else begin
                end
                if (i < 11 && bcd_temp[11:8] > 4) begin
                    bcd_temp[11:8] <= bcd_temp[11:8] + 3;
                end else begin
                end
                if (i < 11 && bcd_temp[15:12] > 4) begin
                    bcd_temp[15:12] <= bcd_temp[15:12] + 3;
                end else begin
                end
                state <= BCD;
                i <= i + 1;
            end
            OUTPUT: begin
                bcd_temp <= 0;
                state <= IDLE;
            end
            endcase
        end
    end


    // always_comb begin
    //     for (i = 0; i < 12; i = i + 1) begin
    //         bcd = {bcd[14:0],bin[7-i]};
    //         //if a hex digit of 'bcd' is more than 4, add 3 to it.  
    //         if (i < 7 && bcd[3:0] > 4) begin
    //             bcd[3:0] = bcd[3:0]+ 3;
    //         end
    //         if (i < 7 && bcd[7:4] > 4) begin
    //             bcd[7:4] = bcd[7:4]+ 3;
    //         end
    //         if (i < 7 && bcd[11:8] > 4) begin
    //             bcd[11:8] = bcd[11:8]+ 3;
    //         end
    //         if (i < 7 && bcd[15:12] > 4) begin
    //             bcd[15:12] = bcd[15:12]+ 3;
    //         end
    //     end
    // end

endmodule


`default_nettype none

final_project/sim/bcd_tb.sv
`timescale 1ns / 1ps
`default_nettype none

module bcd_tb;

    //make logics for inputs and outputs!
    logic clk_in;
    logic rst_in;
    logic data_valid_in;
    logic [11:0] bin;
    logic [15:0] bcd;

    bin2bcd uut(
        .clk_in(clk_in),
        .rst_in(rst_in),  
        .data_valid_in(data_valid_in),    
        .bin(bin),
        .bcd_out(bcd)
    );
    always begin
        #5;  //every 5 ns switch...so period of clock is 10 ns...100 MHz clock
        clk_in = !clk_in;
    end

    //initial block...this is our test simulation
    initial begin
        $dumpfile("bcd.vcd"); //file to store value change dump (vcd)
        $dumpvars(0,bcd_tb); //store everything at the current level and below
        $display("Starting Sim"); //print nice message
        clk_in = 0; //initialize clk (super important)
        rst_in = 0; //initialize rst (super important)
        #10
        rst_in = 1;
        #100;
        rst_in = 0;
        #10;
        bin = 1258;
        #10;
        data_valid_in = 1;
        #10
        data_valid_in = 0;
        #10000;
        bin = 3731;
        #10;
        data_valid_in = 1;
        #10
        data_valid_in = 0;
        #10000;
        
        $display("Finishing Sim"); //print nice message
        $finish;

    end
endmodule //counter_tb

`default_nettype wire

final_project/sim/bcd.vcd
$date
	Thu Dec 14 19:27:46 2023
$end
$version
	Icarus Verilog
$end
$timescale
	1ps
$end
$scope module bcd_tb $end
$var wire 16 ! bcd [15:0] $end
$var reg 12 " bin [11:0] $end
$var reg 1 # clk_in $end
$var reg 1 $ data_valid_in $end
$var reg 1 % rst_in $end
$scope module uut $end
$var wire 12 & bin [11:0] $end
$var wire 1 # clk_in $end
$var wire 1 $ data_valid_in $end
$var wire 1 % rst_in $end
$var reg 16 ' bcd_out [15:0] $end
$var reg 16 ( bcd_temp [15:0] $end
$var reg 5 ) i [4:0] $end
$var integer 32 * state [31:0] $end
$upscope $end
$upscope $end
$enddefinitions $end
$comment Show the parameter values. $end
$dumpall
$end
#0
$dumpvars
b0 *
bx )
bx (
bx '
bx &
0%
x$
0#
bx "
bx !
$end
#5000
1#
#10000
0#
1%
#15000
b1 *
b0 )
b0 !
b0 '
b0 (
1#
#20000
0#
#25000
1#
#30000
0#
#35000
1#
#40000
0#
#45000
1#
#50000
0#
#55000
1#
#60000
0#
#65000
1#
#70000
0#
#75000
1#
#80000
0#
#85000
1#
#90000
0#
#95000
1#
#100000
0#
#105000
1#
#110000
0#
0%
#115000
b10 *
1#
#120000
0#
b10011101010 "
b10011101010 &
#125000
b11 *
1#
#130000
0#
1$
#135000
b1 )
b10 *
1#
#140000
0#
0$
#145000
b11 *
b1 (
1#
#150000
0#
#155000
b10 )
b10 *
1#
#160000
0#
#165000
b11 *
b10 (
1#
#170000
0#
#175000
b11 )
b10 *
1#
#180000
0#
#185000
b11 *
b100 (
1#
#190000
0#
#195000
b100 )
b10 *
1#
#200000
0#
#205000
b11 *
b1001 (
1#
#210000
0#
#215000
b101 )
b10 *
b1100 (
1#
#220000
0#
#225000
b11 *
b11001 (
1#
#230000
0#
#235000
b110 )
b10 *
b11100 (
1#
#240000
0#
#245000
b11 *
b111001 (
1#
#250000
0#
#255000
b111 )
b10 *
b111100 (
1#
#260000
0#
#265000
b11 *
b1111000 (
1#
#270000
0#
#275000
b1000 )
b10 *
b10101011 (
1#
#280000
0#
#285000
b11 *
b101010111 (
1#
#290000
0#
#295000
b1001 )
b10 *
b110001010 (
1#
#300000
0#
#305000
b11 *
b1100010100 (
1#
#310000
0#
#315000
b1010 )
b10 *
1#
#320000
0#
#325000
b11 *
b11000101001 (
1#
#330000
0#
#335000
b1011 )
b10 *
b100100101100 (
1#
#340000
0#
#345000
b11 *
b1001001011000 (
1#
#350000
0#
#355000
b1100 )
b10 *
1#
#360000
0#
#365000
b100 *
b0 )
b1001001011000 !
b1001001011000 '
1#
#370000
0#
#375000
b0 *
b0 (
1#
